mdstruct/__init__.py
mdstruct/cli.py
mdstruct/core.py
mdstruct-1.3.0.dist-info/METADATA
mdstruct-1.3.0.dist-info/WHEEL
mdstruct-1.3.0.dist-info/entry_points.txt
mdstruct-1.3.0.dist-info/licenses/LICENSE
mdstruct-1.3.0.dist-info/RECORD
