Metadata-Version: 2.4
Name: mdstruct
Version: 1.3.0
Summary: Split and recombine markdown files by ATX headers
Project-URL: Repository, https://github.com/DJRHails/mdstruct
Author-email: DJRHails <daniel@hails.info>
License: MIT
License-File: LICENSE
Keywords: cli,headers,join,markdown,split
Classifier: Development Status :: 3 - Alpha
Classifier: Intended Audience :: Developers
Classifier: License :: OSI Approved :: MIT License
Classifier: Programming Language :: Python :: 3
Classifier: Programming Language :: Python :: 3.10
Classifier: Programming Language :: Python :: 3.11
Classifier: Programming Language :: Python :: 3.12
Requires-Python: >=3.10
Requires-Dist: rich>=13.0.0
Requires-Dist: typer>=0.12.0
Provides-Extra: dev
Requires-Dist: bumpver>=2023.1129; extra == 'dev'
Requires-Dist: pre-commit>=4.0.0; extra == 'dev'
Requires-Dist: pytest-cov>=4.1.0; extra == 'dev'
Requires-Dist: pytest>=8.0.0; extra == 'dev'
Requires-Dist: ruff>=0.8.0; extra == 'dev'
